LICENSE
README.md
pyproject.toml
setup.cfg
setup.py
m_validate_import_file.egg-info/PKG-INFO
m_validate_import_file.egg-info/SOURCES.txt
m_validate_import_file.egg-info/dependency_links.txt
m_validate_import_file.egg-info/requires.txt
m_validate_import_file.egg-info/top_level.txt
mobio/libs/validate_import_file/__init__.py
mobio/libs/validate_import_file/common.py
mobio/libs/validate_import_file/utils.py
mobio/libs/validate_import_file/validate.py