Metadata-Version: 2.2
Name: m-validate-import-file
Version: 0.0.3
Summary: Mobio Validate Import File Libs
Home-page: https://github.com/mobiovn
Author: MOBIO
Author-email: contact@mobio.vn
License: MIT
Project-URL: Source, https://github.com/mobiovn
Keywords: mobio,validate-import-file,contact spam
Classifier: Development Status :: 3 - Alpha
Classifier: Intended Audience :: Developers
Classifier: Topic :: Software Development :: Build Tools
Classifier: License :: OSI Approved :: MIT License
Classifier: Programming Language :: Python :: 3.11
Requires-Python: >=3
License-File: LICENSE
Requires-Dist: m-formatter-logging
Requires-Dist: m-filetypes
Requires-Dist: python_calamine==0.1.7
Requires-Dist: m-monitor
Dynamic: author
Dynamic: author-email
Dynamic: classifier
Dynamic: description
Dynamic: description-content-type
Dynamic: home-page
Dynamic: keywords
Dynamic: license
Dynamic: project-url
Dynamic: requires-dist
Dynamic: requires-python
Dynamic: summary
